django_stagers/__init__.py
django_stagers/fields.py
django_stagers/stager.py
django_stagers-0.0.10.dist-info/LICENSE
django_stagers-0.0.10.dist-info/METADATA
django_stagers-0.0.10.dist-info/WHEEL
django_stagers-0.0.10.dist-info/top_level.txt
django_stagers-0.0.10.dist-info/RECORD
